MANIFEST.in
README.md
setup.py
examples/README.md
examples/topological_sorter.py
py_sdag2.egg-info/PKG-INFO
py_sdag2.egg-info/SOURCES.txt
py_sdag2.egg-info/dependency_links.txt
py_sdag2.egg-info/top_level.txt
scripts/tsort.py
sdag2/__init__.py
sdag2/sdag2.py