Metadata-Version: 1.1
Name: py_sdag2
Version: 1.0.1
Summary: Simple Directed Acyclic Graph whith Cicle Detector and TopoloGical sorter utilities.
Home-page: https://github.com/moisespsena/py_sdag2
Author: Moises P. Sena
Author-email: moisespsena@gmail.com
License: BSD
Keywords: utils utilities directed graph digraph topological simple dag
Platform: UNKNOWN
Classifier: Development Status :: 5 - Production/Stable
Classifier: Topic :: Utilities
Classifier: Intended Audience :: Developers
Classifier: License :: OSI Approved :: BSD License
Classifier: Operating System :: OS Independent
Classifier: Programming Language :: Python :: 2
Classifier: Programming Language :: Python :: 2.7
Classifier: Programming Language :: Python :: 3
Classifier: Programming Language :: Python :: 3.2
